cerochat/__init__.py
cerochat/chat.py
cerochat/config.py
cerochat/database.py
cerochat/exceptions.py
cerochat/main.py
cerochat-0.1.0.dist-info/METADATA
cerochat-0.1.0.dist-info/WHEEL
cerochat-0.1.0.dist-info/entry_points.txt
cerochat-0.1.0.dist-info/top_level.txt
cerochat-0.1.0.dist-info/RECORD
